konsole/__init__.py
konsole/py.typed
konsole-0.7.0.dist-info/LICENSE
konsole-0.7.0.dist-info/WHEEL
konsole-0.7.0.dist-info/METADATA
konsole-0.7.0.dist-info/RECORD
