Metadata-Version: 2.1
Name: konsole
Version: 0.7.0
Summary: konsole: readable, pleasing console output
Author-email: Robert Grimm <apparebit@gmail.com>
Requires-Python: >=3.7
Classifier: Environment :: Console
Classifier: License :: OSI Approved :: Apache Software License
Classifier: Operating System :: OS Independent
Classifier: Programming Language :: Python
Classifier: Programming Language :: Python :: 3 :: Only
Classifier: Programming Language :: Python :: 3.7
Classifier: Programming Language :: Python :: 3.8
Classifier: Programming Language :: Python :: 3.9
Classifier: Programming Language :: Python :: 3.10
Classifier: Topic :: Utilities
Requires-Dist: black ; extra == "dev"
Requires-Dist: flit ; extra == "dev"
Requires-Dist: mypy ; extra == "dev"
Project-URL: Home, https://github.com/apparebit/konsole
Provides-Extra: dev
